Workbook

Sheet Cover
B2: DunongAI
B3: An AI-Powered Adaptive Reading Companion
B5: FINANCIAL PLAN — YEAR 1 (MONTHLY)
B6: Income Statement • Cash Flow Statement • Balance Sheet
B8: All figures in Philippine Pesos (PHP / ₱) unless stated otherwise.
B9: Prepared by: Cantos, Labay, Gamboa, Delos Santos (Group 4)
B11: How to use this model:
B12: • Blue cells are inputs/assumptions — change them to test scenarios.
B13: • Black cells are formulas; green cells link across sheets. All totals recalculate automatically.
B14: • Start on the 'Assumptions' tab, then review the three statements.
B16: Tabs: Assumptions › Income Statement › Cash Flow › Balance Sheet

Sheet Assumptions
A1: Assumptions & Drivers
A2: DunongAI — Year 1 (Monthly). Blue = input. Edit these to drive every statement.
A4: PRICING & UNIT ECONOMICS
A5: Parent freemium subscription price (₱ / month) | C5: 99 | D5: BMC/SWOT: ₱99/mo parent tier
A6: DepEd institutional license (₱ / learner / year) | C6: 8 | D6: SWOT Scenario A: ₱8/learner/yr ceiling
A7: AI inference cost — Claude Haiku (₱ / session) | C7: 0.08 | D7: SWOT ST move: ≤₱0.08/session
A8: Avg reading sessions per active learner / month | C8: 10 | D8: Roadmap: ≥3 sessions/week
A9: Content development cost (₱ / leveled story) | C9: 400 | D9: TOWS WO move: ≤₱400/story
A10: Percentage / business tax (% of commercial revenue) | C10: 0.03 | D10: PH non-VAT, <₱3M receipts
A11: Equipment depreciation period (months) | C11: 36
A12: Platform-dev amortization period (months) | C12: 36
A14: CAPITAL & ONE-TIME (Month 1)
A15: Founders' + pre-seed capital injected (₱) | C15: 1500000 | D15: Pre-seed; seed round opens Q4
A16: Equipment capex — laptops/devices (₱) | C16: 150000
A17: Capitalized platform development (₱) | C17: 300000 | D17: MVP build capitalized as intangible
A19: GRANT FUNDING — non-dilutive (₱)
A20: DOST PCIEERD grant — tranche 1 (received Month 4) | C20: 400000 | D20: SWOT: DOST PCIEERD
A21: USAID ABC+ grant — tranche 2 (received Month 9) | C21: 400000 | D21: SWOT: USAID ABC+
A24: MONTHLY OPERATING DRIVERS | B24: Month 1 | C24: Month 2 | D24: Month 3 | E24: Month 4 | F24: Month 5 | G24: Month 6 | H24: Month 7 | I24: Month 8 | J24: Month 9 | K24: Month 10 | L24: Month 11 | M24: Month 12
A25: Total active learners on platform | B25: 200 | C25: 300 | D25: 450 | E25: 650 | F25: 1000 | G25: 1500 | H25: 3000 | I25: 5000 | J25: 6500 | K25: 12000 | L25: 14000 | M25: 16000
A26: of which: paying parents (₱99 tier) | B26: 0 | C26: 0 | D26: 0 | E26: 0 | F26: 0 | G26: 0 | H26: 120 | I26: 250 | J26: 420 | K26: 600 | L26: 800 | M26: 1010
A27: of which: DepEd institutional learners (paid) | B27: 0 | C27: 0 | D27: 0 | E27: 0 | F27: 0 | G27: 0 | H27: 0 | I27: 0 | J27: 0 | K27: 5000 | L27: 5000 | M27: 5000
A28: Reading sessions (= active × sessions/learner) | B28: =B25*$C$8 -> 2000 | C28: =C25*$C$8 -> 3000 | D28: =D25*$C$8 -> 4500 | E28: =E25*$C$8 -> 6500 | F28: =F25*$C$8 -> 10000 | G28: =G25*$C$8 -> 15000 | H28: =H25*$C$8 -> 30000 | I28: =I25*$C$8 -> 50000 | ... M28: =M25*$C$8 -> 160000

Sheet Income Statement
A1: Income Statement (Profit & Loss)
A2: DunongAI — Year 1, monthly (PHP). Revenues − expenses = net profit/(loss).
B3: Month 1 | C3: Month 2 | D3: Month 3 | E3: Month 4 | F3: Month 5 | G3: Month 6 | H3: Month 7 | I3: Month 8 | J3: Month 9 | K3: Month 10 | L3: Month 11 | M3: Month 12 | N3: Year 1 Total
A4: REVENUES
A5: Parent subscription revenue | B5: =Assumptions!B26*Assumptions!$C$5 -> 0 | C5: =Assumptions!C26*Assumptions!$C$5 -> 0 | D5: =Assumptions!D26*Assumptions!$C$5 -> 0 | E5: =Assumptions!E26*Assumptions!$C$5 -> 0 | F5: =Assumptions!F26*Assumptions!$C$5 -> 0 | G5: =Assumptions!G26*Assumptions!$C$5 -> 0 | H5: =Assumptions!H26*Assumptions!$C$5 -> 11880 | I5: =Assumptions!I26*Assumptions!$C$5 -> 24750 | ... M5: =Assumptions!M26*Assumptions!$C$5 -> 99990 | N5: =SUM(B5:M5) -> 316800
A6: DepEd institutional license (recognized) | B6: =Assumptions!B27*Assumptions!$C$6/12 -> 0 | C6: =Assumptions!C27*Assumptions!$C$6/12 -> 0 | D6: =Assumptions!D27*Assumptions!$C$6/12 -> 0 | E6: =Assumptions!E27*Assumptions!$C$6/12 -> 0 | F6: =Assumptions!F27*Assumptions!$C$6/12 -> 0 | G6: =Assumptions!G27*Assumptions!$C$6/12 -> 0 | H6: =Assumptions!H27*Assumptions!$C$6/12 -> 0 | I6: =Assumptions!I27*Assumptions!$C$6/12 -> 0 | ... M6: =Assumptions!M27*Assumptions!$C$6/12 -> 3333.3333 | N6: =SUM(B6:M6) -> 10000
A7: Grant income (DOST / USAID, recognized) | B7: 0 | C7: 0 | D7: 0 | E7: =Assumptions!$C$20 -> 400000 | F7: 0 | G7: 0 | H7: 0 | I7: 0 | J7: =Assumptions!$C$21 -> 400000 | K7: 0 | L7: 0 | M7: 0 | N7: =SUM(B7:M7) -> 800000
A8: Total Revenue | B8: =SUM(B5:B7) -> 0 | C8: =SUM(C5:C7) -> 0 | D8: =SUM(D5:D7) -> 0 | E8: =SUM(E5:E7) -> 400000 | F8: =SUM(F5:F7) -> 0 | G8: =SUM(G5:G7) -> 0 | H8: =SUM(H5:H7) -> 11880 | I8: =SUM(I5:I7) -> 24750 | ... M8: =SUM(M5:M7) -> 103323.33 | N8: =SUM(B8:M8) -> 1126800
A10: COST OF GOODS SOLD (direct service delivery)
A11: AI inference — Claude Haiku | B11: =Assumptions!B28*Assumptions!$C$7 -> 160 | C11: =Assumptions!C28*Assumptions!$C$7 -> 240 | D11: =Assumptions!D28*Assumptions!$C$7 -> 360 | E11: =Assumptions!E28*Assumptions!$C$7 -> 520 | F11: =Assumptions!F28*Assumptions!$C$7 -> 800 | G11: =Assumptions!G28*Assumptions!$C$7 -> 1200 | H11: =Assumptions!H28*Assumptions!$C$7 -> 2400 | I11: =Assumptions!I28*Assumptions!$C$7 -> 4000 | ... M11: =Assumptions!M28*Assumptions!$C$7 -> 12800 | N11: =SUM(B11:M11) -> 48480
A12: Content development (leveled stories) | B12: 20000 | C12: 20000 | D12: 12000 | E12: 8000 | F12: 2000 | G12: 2000 | H12: 2000 | I12: 2000 | J12: 2000 | K12: 2000 | L12: 2000 | M12: 2000 | N12: =SUM(B12:M12) -> 76000
A13: Total COGS | B13: =SUM(B11:B12) -> 20160 | C13: =SUM(C11:C12) -> 20240 | D13: =SUM(D11:D12) -> 12360 | E13: =SUM(E11:E12) -> 8520 | F13: =SUM(F11:F12) -> 2800 | G13: =SUM(G11:G12) -> 3200 | H13: =SUM(H11:H12) -> 4400 | I13: =SUM(I11:I12) -> 6000 | ... M13: =SUM(M11:M12) -> 14800 | N13: =SUM(B13:M13) -> 124480
A14: GROSS PROFIT | B14: =B8-B13 -> -20160 | C14: =C8-C13 -> -20240 | D14: =D8-D13 -> -12360 | E14: =E8-E13 -> 391480 | F14: =F8-F13 -> -2800 | G14: =G8-G13 -> -3200 | H14: =H8-H13 -> 7480 | I14: =I8-I13 -> 18750 | ... M14: =M8-M13 -> 88523.333 | N14: =SUM(B14:M14) -> 1002320
A15: Gross profit margin | B15: =IF(B8=0,0,B14/B8) -> 0 | C15: =IF(C8=0,0,C14/C8) -> 0 | D15: =IF(D8=0,0,D14/D8) -> 0 | E15: =IF(E8=0,0,E14/E8) -> 0.9787 | F15: =IF(F8=0,0,F14/F8) -> 0 | G15: =IF(G8=0,0,G14/G8) -> 0 | H15: =IF(H8=0,0,H14/H8) -> 0.62962963 | I15: =IF(I8=0,0,I14/I8) -> 0.75757576 | ... N15: =IF(N8=0,0,N14/N8) -> 0.88952787
A17: OPERATING EXPENSES
A18: Salaries & founder stipends | B18: 40000 | C18: 40000 | D18: 40000 | E18: 60000 | F18: 60000 | G18: 60000 | H18: 100000 | I18: 100000 | J18: 100000 | K18: 100000 | L18: 100000 | M18: 100000 | N18: =SUM(B18:M18) -> 900000
A19: Cloud infrastructure (Firebase/Vercel) | B19: 3000 | C19: 3000 | D19: 3000 | E19: 3000 | F19: 3000 | G19: 3000 | H19: 3000 | I19: 3000 | J19: 3000 | K19: 3000 | L19: 3000 | M19: 3000 | N19: =SUM(B19:M19) -> 36000
A20: Internet & communications | B20: 2500 | C20: 2500 | D20: 2500 | E20: 2500 | F20: 2500 | G20: 2500 | H20: 2500 | I20: 2500 | J20: 2500 | K20: 2500 | L20: 2500 | M20: 2500 | N20: =SUM(B20:M20) -> 30000
A21: Software & tools | B21: 2000 | C21: 2000 | D21: 2000 | E21: 2000 | F21: 2000 | G21: 2000 | H21: 2000 | I21: 2000 | J21: 2000 | K21: 2000 | L21: 2000 | M21: 2000 | N21: =SUM(B21:M21) -> 24000
A22: Marketing & user acquisition | B22: 3000 | C22: 3000 | D22: 3000 | E22: 3000 | F22: 3000 | G22: 3000 | H22: 20000 | I22: 20000 | J22: 20000 | K22: 20000 | L22: 20000 | M22: 20000 | N22: =SUM(B22:M22) -> 138000
A23: Pilot program costs (incentives, travel) | B23: 40000 | C23: 40000 | D23: 30000 | E23: 5000 | F23: 5000 | G23: 5000 | H23: 0 | I23: 0 | J23: 0 | K23: 0 | L23: 0 | M23: 0 | N23: =SUM(B23:M23) -> 125000
A24: Research & compliance (DPA/NPC/IRB/audit) | B24: 0 | C24: 25000 | D24: 30000 | E24: 0 | F24: 0 | G24: 20000 | H24: 0 | I24: 0 | J24: 20000 | K24: 0 | L24: 0 | M24: 0 | N24: =SUM(B24:M24) -> 95000
A25: Professional & registration fees | B25: 15000 | C25: 3000 | D25: 3000 | E25: 3000 | F25: 3000 | G25: 3000 | H25: 3000 | I25: 3000 | J25: 3000 | K25: 3000 | L25: 3000 | M25: 3000 | N25: =SUM(B25:M25) -> 48000
A26: Depreciation — equipment | B26: =Assumptions!$C$16/Assumptions!$C$11 -> 4166.6667 | C26: =Assumptions!$C$16/Assumptions!$C$11 -> 4166.6667 | D26: =Assumptions!$C$16/Assumptions!$C$11 -> 4166.6667 | E26: =Assumptions!$C$16/Assumptions!$C$11 -> 4166.6667 | F26: =Assumptions!$C$16/Assumptions!$C$11 -> 4166.6667 | G26: =Assumptions!$C$16/Assumptions!$C$11 -> 4166.6667 | H26: =Assumptions!$C$16/Assumptions!$C$11 -> 4166.6667 | I26: =Assumptions!$C$16/Assumptions!$C$11 -> 4166.6667 | ... M26: =Assumptions!$C$16/Assumptions!$C$11 -> 4166.6667 | N26: =SUM(B26:M26) -> 50000
A27: Amortization — platform development | B27: =Assumptions!$C$17/Assumptions!$C$12 -> 8333.3333 | C27: =Assumptions!$C$17/Assumptions!$C$12 -> 8333.3333 | D27: =Assumptions!$C$17/Assumptions!$C$12 -> 8333.3333 | E27: =Assumptions!$C$17/Assumptions!$C$12 -> 8333.3333 | F27: =Assumptions!$C$17/Assumptions!$C$12 -> 8333.3333 | G27: =Assumptions!$C$17/Assumptions!$C$12 -> 8333.3333 | H27: =Assumptions!$C$17/Assumptions!$C$12 -> 8333.3333 | I27: =Assumptions!$C$17/Assumptions!$C$12 -> 8333.3333 | ... M27: =Assumptions!$C$17/Assumptions!$C$12 -> 8333.3333 | N27: =SUM(B27:M27) -> 100000
A28: Total Operating Expenses | B28: =SUM(B18:B27) -> 118000 | C28: =SUM(C18:C27) -> 131000 | D28: =SUM(D18:D27) -> 126000 | E28: =SUM(E18:E27) -> 91000 | F28: =SUM(F18:F27) -> 91000 | G28: =SUM(G18:G27) -> 111000 | H28: =SUM(H18:H27) -> 143000 | I28: =SUM(I18:I27) -> 143000 | ... M28: =SUM(M18:M27) -> 143000 | N28: =SUM(B28:M28) -> 1546000
A30: EBITDA | B30: =B14-(B28-B26-B27) -> -125660 | C30: =C14-(C28-C26-C27) -> -138740 | D30: =D14-(D28-D26-D27) -> -125860 | E30: =E14-(E28-E26-E27) -> 312980 | F30: =F14-(F28-F26-F27) -> -81300 | G30: =G14-(G28-G26-G27) -> -101700 | H30: =H14-(H28-H26-H27) -> -123020 | I30: =I14-(I28-I26-I27) -> -111750 | ... M30: =M14-(M28-M26-M27) -> -41976.667 | N30: =SUM(B30:M30) -> -393680
A31: EBIT (Operating income) | B31: =B14-B28 -> -138160 | C31: =C14-C28 -> -151240 | D31: =D14-D28 -> -138360 | E31: =E14-E28 -> 300480 | F31: =F14-F28 -> -93800 | G31: =G14-G28 -> -114200 | H31: =H14-H28 -> -135520 | I31: =I14-I28 -> -124250 | ... M31: =M14-M28 -> -54476.667 | N31: =SUM(B31:M31) -> -543680
A32: Interest expense | B32: 0 | C32: 0 | D32: 0 | E32: 0 | F32: 0 | G32: 0 | H32: 0 | I32: 0 | J32: 0 | K32: 0 | L32: 0 | M32: 0 | N32: =SUM(B32:M32) -> 0
A33: Pre-tax income / (loss) | B33: =B31-B32 -> -138160 | C33: =C31-C32 -> -151240 | D33: =D31-D32 -> -138360 | E33: =E31-E32 -> 300480 | F33: =F31-F32 -> -93800 | G33: =G31-G32 -> -114200 | H33: =H31-H32 -> -135520 | I33: =I31-I32 -> -124250 | ... M33: =M31-M32 -> -54476.667 | N33: =SUM(B33:M33) -> -543680
A34: Percentage / business tax | B34: =(B5+B6)*Assumptions!$C$10 -> 0 | C34: =(C5+C6)*Assumptions!$C$10 -> 0 | D34: =(D5+D6)*Assumptions!$C$10 -> 0 | E34: =(E5+E6)*Assumptions!$C$10 -> 0 | F34: =(F5+F6)*Assumptions!$C$10 -> 0 | G34: =(G5+G6)*Assumptions!$C$10 -> 0 | H34: =(H5+H6)*Assumptions!$C$10 -> 356.4 | I34: =(I5+I6)*Assumptions!$C$10 -> 742.5 | ... M34: =(M5+M6)*Assumptions!$C$10 -> 3099.7 | N34: =SUM(B34:M34) -> 9804
A35: NET PROFIT / (LOSS) | B35: =B33-B34 -> -138160 | C35: =C33-C34 -> -151240 | D35: =D33-D34 -> -138360 | E35: =E33-E34 -> 300480 | F35: =F33-F34 -> -93800 | G35: =G33-G34 -> -114200 | H35: =H33-H34 -> -135876.4 | I35: =I33-I34 -> -124992.5 | ... M35: =M33-M34 -> -57576.367 | N35: =SUM(B35:M35) -> -553484
A36: Net profit margin | B36: =IF(B8=0,0,B35/B8) -> 0 | C36: =IF(C8=0,0,C35/C8) -> 0 | D36: =IF(D8=0,0,D35/D8) -> 0 | E36: =IF(E8=0,0,E35/E8) -> 0.7512 | F36: =IF(F8=0,0,F35/F8) -> 0 | G36: =IF(G8=0,0,G35/G8) -> 0 | H36: =IF(H8=0,0,H35/H8) -> -11.437407 | I36: =IF(I8=0,0,I35/I8) -> -5.050202 | ... N36: =IF(N8=0,0,N35/N8) -> -0.49119986

Sheet Cash Flow
A1: Cash Flow Statement
A2: DunongAI — Year 1, monthly (PHP). Direct method: cash in − cash out.
B3: Month 1 | C3: Month 2 | D3: Month 3 | E3: Month 4 | F3: Month 5 | G3: Month 6 | H3: Month 7 | I3: Month 8 | J3: Month 9 | K3: Month 10 | L3: Month 11 | M3: Month 12 | N3: Year 1 Total
A4: OPERATING ACTIVITIES
A5: Collections — parent subscriptions | B5: ='Income Statement'!B5 -> 0 | C5: ='Income Statement'!C5 -> 0 | D5: ='Income Statement'!D5 -> 0 | E5: ='Income Statement'!E5 -> 0 | F5: ='Income Statement'!F5 -> 0 | G5: ='Income Statement'!G5 -> 0 | H5: ='Income Statement'!H5 -> 11880 | I5: ='Income Statement'!I5 -> 24750 | ... M5: ='Income Statement'!M5 -> 99990 | N5: =SUM(B5:M5) -> 316800
A6: Collections — DepEd license (annual upfront) | B6: 0 | C6: 0 | D6: 0 | E6: 0 | F6: 0 | G6: 0 | H6: 0 | I6: 0 | J6: 0 | K6: 40000 | L6: 0 | M6: 0 | N6: =SUM(B6:M6) -> 40000
A7: Grant receipts (DOST / USAID) | B7: ='Income Statement'!B7 -> 0 | C7: ='Income Statement'!C7 -> 0 | D7: ='Income Statement'!D7 -> 0 | E7: ='Income Statement'!E7 -> 400000 | F7: ='Income Statement'!F7 -> 0 | G7: ='Income Statement'!G7 -> 0 | H7: ='Income Statement'!H7 -> 0 | I7: ='Income Statement'!I7 -> 0 | ... M7: ='Income Statement'!M7 -> 0 | N7: =SUM(B7:M7) -> 800000
A8: COGS paid | B8: =-'Income Statement'!B13 -> -20160 | C8: =-'Income Statement'!C13 -> -20240 | D8: =-'Income Statement'!D13 -> -12360 | E8: =-'Income Statement'!E13 -> -8520 | F8: =-'Income Statement'!F13 -> -2800 | G8: =-'Income Statement'!G13 -> -3200 | H8: =-'Income Statement'!H13 -> -4400 | I8: =-'Income Statement'!I13 -> -6000 | ... M8: =-'Income Statement'!M13 -> -14800 | N8: =SUM(B8:M8) -> -124480
A9: Operating expenses paid (excl. D&A) | B9: =-('Income Statement'!B28-'Income Statement'!B26-'Income Statement'!B27) -> -105500 | C9: =-('Income Statement'!C28-'Income Statement'!C26-'Income Statement'!C27) -> -118500 | D9: =-('Income Statement'!D28-'Income Statement'!D26-'Income Statement'!D27) -> -113500 | E9: =-('Income Statement'!E28-'Income Statement'!E26-'Income Statement'!E27) -> -78500 | F9: =-('Income Statement'!F28-'Income Statement'!F26-'Income Statement'!F27) -> -78500 | G9: =-('Income Statement'!G28-'Income Statement'!G26-'Income Statement'!G27) -> -98500 | H9: =-('Income Statement'!H28-'Income Statement'!H26-'Income Statement'!H27) -> -130500 | I9: =-('Income Statement'!I28-'Income Statement'!I26-'Income Statement'!I27) -> -130500 | ... M9: =-('Income Statement'!M28-'Income Statement'!M26-'Income Statement'!M27) -> -130500 | N9: =SUM(B9:M9) -> -1396000
A10: Taxes paid | B10: =-'Income Statement'!B34 -> 0 | C10: =-'Income Statement'!C34 -> 0 | D10: =-'Income Statement'!D34 -> 0 | E10: =-'Income Statement'!E34 -> 0 | F10: =-'Income Statement'!F34 -> 0 | G10: =-'Income Statement'!G34 -> 0 | H10: =-'Income Statement'!H34 -> -356.4 | I10: =-'Income Statement'!I34 -> -742.5 | ... M10: =-'Income Statement'!M34 -> -3099.7 | N10: =SUM(B10:M10) -> -9804
A11: Net cash from operations | B11: =SUM(B5:B10) -> -125660 | C11: =SUM(C5:C10) -> -138740 | D11: =SUM(D5:D10) -> -125860 | E11: =SUM(E5:E10) -> 312980 | F11: =SUM(F5:F10) -> -81300 | G11: =SUM(G5:G10) -> -101700 | H11: =SUM(H5:H10) -> -123376.4 | I11: =SUM(I5:I10) -> -112492.5 | ... M11: =SUM(M5:M10) -> -48409.7 | N11: =SUM(B11:M11) -> -373484
A13: INVESTING ACTIVITIES
A14: Equipment purchase | B14: =-Assumptions!$C$16 -> -150000 | C14: 0 | D14: 0 | E14: 0 | F14: 0 | G14: 0 | H14: 0 | I14: 0 | J14: 0 | K14: 0 | L14: 0 | M14: 0 | N14: =SUM(B14:M14) -> -150000
A15: Capitalized platform development | B15: =-Assumptions!$C$17 -> -300000 | C15: 0 | D15: 0 | E15: 0 | F15: 0 | G15: 0 | H15: 0 | I15: 0 | J15: 0 | K15: 0 | L15: 0 | M15: 0 | N15: =SUM(B15:M15) -> -300000
A16: Net cash from investing | B16: =SUM(B14:B15) -> -450000 | C16: =SUM(C14:C15) -> 0 | D16: =SUM(D14:D15) -> 0 | E16: =SUM(E14:E15) -> 0 | F16: =SUM(F14:F15) -> 0 | G16: =SUM(G14:G15) -> 0 | H16: =SUM(H14:H15) -> 0 | I16: =SUM(I14:I15) -> 0 | ... M16: =SUM(M14:M15) -> 0 | N16: =SUM(B16:M16) -> -450000
A18: FINANCING ACTIVITIES
A19: Founders' + pre-seed capital | B19: =Assumptions!$C$15 -> 1500000 | C19: 0 | D19: 0 | E19: 0 | F19: 0 | G19: 0 | H19: 0 | I19: 0 | J19: 0 | K19: 0 | L19: 0 | M19: 0 | N19: =SUM(B19:M19) -> 1500000
A20: Net cash from financing | B20: =B19 -> 1500000 | C20: =C19 -> 0 | D20: =D19 -> 0 | E20: =E19 -> 0 | F20: =F19 -> 0 | G20: =G19 -> 0 | H20: =H19 -> 0 | I20: =I19 -> 0 | ... M20: =M19 -> 0 | N20: =SUM(B20:M20) -> 1500000
A22: Net change in cash | B22: =B11+B16+B20 -> 924340 | C22: =C11+C16+C20 -> -138740 | D22: =D11+D16+D20 -> -125860 | E22: =E11+E16+E20 -> 312980 | F22: =F11+F16+F20 -> -81300 | G22: =G11+G16+G20 -> -101700 | H22: =H11+H16+H20 -> -123376.4 | I22: =I11+I16+I20 -> -112492.5 | ... M22: =M11+M16+M20 -> -48409.7 | N22: =SUM(B22:M22) -> 676516
A23: Opening cash balance | B23: 0 | C23: =B24 -> 924340 | D23: =C24 -> 785600 | E23: =D24 -> 659740 | F23: =E24 -> 972720 | G23: =F24 -> 891420 | H23: =G24 -> 789720 | I23: =H24 -> 666343.6 | J23: =I24 -> 553851.1 | ... M23: =L24 -> 724925.7 | N23: =B23 -> 0
A24: Closing cash balance | B24: =B23+B22 -> 924340 | C24: =C23+C22 -> 785600 | D24: =D23+D22 -> 659740 | E24: =E23+E22 -> 972720 | F24: =F23+F22 -> 891420 | G24: =G23+G22 -> 789720 | H24: =H23+H22 -> 666343.6 | I24: =I23+I22 -> 553851.1 | ... M24: =M23+M22 -> 676516 | N24: =M24 -> 676516

Sheet Balance Sheet
A1: Balance Sheet
A2: DunongAI — end of each month, Year 1 (PHP). Assets = Liabilities + Equity.
A3: As of end of | B3: Month 1 | C3: Month 2 | D3: Month 3 | E3: Month 4 | F3: Month 5 | G3: Month 6 | H3: Month 7 | I3: Month 8 | J3: Month 9 | K3: Month 10 | L3: Month 11 | M3: Month 12
A4: ASSETS
A5: Current assets
A6: Cash & cash equivalents | B6: ='Cash Flow'!B24 -> 924340 | C6: ='Cash Flow'!C24 -> 785600 | D6: ='Cash Flow'!D24 -> 659740 | E6: ='Cash Flow'!E24 -> 972720 | F6: ='Cash Flow'!F24 -> 891420 | G6: ='Cash Flow'!G24 -> 789720 | H6: ='Cash Flow'!H24 -> 666343.6 | I6: ='Cash Flow'!I24 -> 553851.1 | ... M6: ='Cash Flow'!M24 -> 676516
A7: Accounts receivable | B7: 0 | C7: 0 | D7: 0 | E7: 0 | F7: 0 | G7: 0 | H7: 0 | I7: 0 | J7: 0 | K7: 0 | L7: 0 | M7: 0
A8: Total current assets | B8: =B6+B7 -> 924340 | C8: =C6+C7 -> 785600 | D8: =D6+D7 -> 659740 | E8: =E6+E7 -> 972720 | F8: =F6+F7 -> 891420 | G8: =G6+G7 -> 789720 | H8: =H6+H7 -> 666343.6 | I8: =I6+I7 -> 553851.1 | ... M8: =M6+M7 -> 676516
A9: Non-current assets
A10: Equipment (at cost) | B10: =Assumptions!$C$16 -> 150000 | C10: =Assumptions!$C$16 -> 150000 | D10: =Assumptions!$C$16 -> 150000 | E10: =Assumptions!$C$16 -> 150000 | F10: =Assumptions!$C$16 -> 150000 | G10: =Assumptions!$C$16 -> 150000 | H10: =Assumptions!$C$16 -> 150000 | I10: =Assumptions!$C$16 -> 150000 | ... M10: =Assumptions!$C$16 -> 150000
A11: Less: accumulated depreciation | B11: =-'Income Statement'!B26 -> -4166.6667 | C11: =B11-'Income Statement'!C26 -> -8333.3333 | D11: =C11-'Income Statement'!D26 -> -12500 | E11: =D11-'Income Statement'!E26 -> -16666.667 | F11: =E11-'Income Statement'!F26 -> -20833.333 | G11: =F11-'Income Statement'!G26 -> -25000 | H11: =G11-'Income Statement'!H26 -> -29166.667 | I11: =H11-'Income Statement'!I26 -> -33333.333 | J11: =I11-'Income Statement'!J26 -> -37500 | ... M11: =L11-'Income Statement'!M26 -> -50000
A12: Equipment, net | B12: =B10+B11 -> 145833.33 | C12: =C10+C11 -> 141666.67 | D12: =D10+D11 -> 137500 | E12: =E10+E11 -> 133333.33 | F12: =F10+F11 -> 129166.67 | G12: =G10+G11 -> 125000 | H12: =H10+H11 -> 120833.33 | I12: =I10+I11 -> 116666.67 | ... M12: =M10+M11 -> 100000
A13: Platform development (at cost) | B13: =Assumptions!$C$17 -> 300000 | C13: =Assumptions!$C$17 -> 300000 | D13: =Assumptions!$C$17 -> 300000 | E13: =Assumptions!$C$17 -> 300000 | F13: =Assumptions!$C$17 -> 300000 | G13: =Assumptions!$C$17 -> 300000 | H13: =Assumptions!$C$17 -> 300000 | I13: =Assumptions!$C$17 -> 300000 | ... M13: =Assumptions!$C$17 -> 300000
A14: Less: accumulated amortization | B14: =-'Income Statement'!B27 -> -8333.3333 | C14: =B14-'Income Statement'!C27 -> -16666.667 | D14: =C14-'Income Statement'!D27 -> -25000 | E14: =D14-'Income Statement'!E27 -> -33333.333 | F14: =E14-'Income Statement'!F27 -> -41666.667 | G14: =F14-'Income Statement'!G27 -> -50000 | H14: =G14-'Income Statement'!H27 -> -58333.333 | I14: =H14-'Income Statement'!I27 -> -66666.667 | J14: =I14-'Income Statement'!J27 -> -75000 | ... M14: =L14-'Income Statement'!M27 -> -100000
A15: Platform development, net | B15: =B13+B14 -> 291666.67 | C15: =C13+C14 -> 283333.33 | D15: =D13+D14 -> 275000 | E15: =E13+E14 -> 266666.67 | F15: =F13+F14 -> 258333.33 | G15: =G13+G14 -> 250000 | H15: =H13+H14 -> 241666.67 | I15: =I13+I14 -> 233333.33 | ... M15: =M13+M14 -> 200000
A16: Total non-current assets | B16: =B12+B15 -> 437500 | C16: =C12+C15 -> 425000 | D16: =D12+D15 -> 412500 | E16: =E12+E15 -> 400000 | F16: =F12+F15 -> 387500 | G16: =G12+G15 -> 375000 | H16: =H12+H15 -> 362500 | I16: =I12+I15 -> 350000 | ... M16: =M12+M15 -> 300000
A17: TOTAL ASSETS | B17: =B8+B16 -> 1361840 | C17: =C8+C16 -> 1210600 | D17: =D8+D16 -> 1072240 | E17: =E8+E16 -> 1372720 | F17: =F8+F16 -> 1278920 | G17: =G8+G16 -> 1164720 | H17: =H8+H16 -> 1028843.6 | I17: =I8+I16 -> 903851.1 | ... M17: =M8+M16 -> 976516
A19: LIABILITIES
A20: Current liabilities
A21: Accounts payable | B21: 0 | C21: 0 | D21: 0 | E21: 0 | F21: 0 | G21: 0 | H21: 0 | I21: 0 | J21: 0 | K21: 0 | L21: 0 | M21: 0
A22: Deferred revenue (DepEd unearned) | B22: =('Cash Flow'!B6-'Income Statement'!B6) -> 0 | C22: =B22+('Cash Flow'!C6-'Income Statement'!C6) -> 0 | D22: =C22+('Cash Flow'!D6-'Income Statement'!D6) -> 0 | E22: =D22+('Cash Flow'!E6-'Income Statement'!E6) -> 0 | F22: =E22+('Cash Flow'!F6-'Income Statement'!F6) -> 0 | G22: =F22+('Cash Flow'!G6-'Income Statement'!G6) -> 0 | H22: =G22+('Cash Flow'!H6-'Income Statement'!H6) -> 0 | I22: =H22+('Cash Flow'!I6-'Income Statement'!I6) -> 0 | J22: =I22+('Cash Flow'!J6-'Income Statement'!J6) -> 0 | ... M22: =L22+('Cash Flow'!M6-'Income Statement'!M6) -> 30000
A23: Total liabilities | B23: =B21+B22 -> 0 | C23: =C21+C22 -> 0 | D23: =D21+D22 -> 0 | E23: =E21+E22 -> 0 | F23: =F21+F22 -> 0 | G23: =G21+G22 -> 0 | H23: =H21+H22 -> 0 | I23: =I21+I22 -> 0 | ... M23: =M21+M22 -> 30000
A25: EQUITY
A26: Paid-in capital | B26: ='Cash Flow'!B19 -> 1500000 | C26: =B26+'Cash Flow'!C19 -> 1500000 | D26: =C26+'Cash Flow'!D19 -> 1500000 | E26: =D26+'Cash Flow'!E19 -> 1500000 | F26: =E26+'Cash Flow'!F19 -> 1500000 | G26: =F26+'Cash Flow'!G19 -> 1500000 | H26: =G26+'Cash Flow'!H19 -> 1500000 | I26: =H26+'Cash Flow'!I19 -> 1500000 | J26: =I26+'Cash Flow'!J19 -> 1500000 | ... M26: =L26+'Cash Flow'!M19 -> 1500000
A27: Retained earnings / (accumulated deficit) | B27: ='Income Statement'!B35 -> -138160 | C27: =B27+'Income Statement'!C35 -> -289400 | D27: =C27+'Income Statement'!D35 -> -427760 | E27: =D27+'Income Statement'!E35 -> -127280 | F27: =E27+'Income Statement'!F35 -> -221080 | G27: =F27+'Income Statement'!G35 -> -335280 | H27: =G27+'Income Statement'!H35 -> -471156.4 | I27: =H27+'Income Statement'!I35 -> -596148.9 | J27: =I27+'Income Statement'!J35 -> -326016.3 | ... M27: =L27+'Income Statement'!M35 -> -553484
A28: Total equity | B28: =B26+B27 -> 1361840 | C28: =C26+C27 -> 1210600 | D28: =D26+D27 -> 1072240 | E28: =E26+E27 -> 1372720 | F28: =F26+F27 -> 1278920 | G28: =G26+G27 -> 1164720 | H28: =H26+H27 -> 1028843.6 | I28: =I26+I27 -> 903851.1 | ... M28: =M26+M27 -> 946516
A29: TOTAL LIABILITIES & EQUITY | B29: =B23+B28 -> 1361840 | C29: =C23+C28 -> 1210600 | D29: =D23+D28 -> 1072240 | E29: =E23+E28 -> 1372720 | F29: =F23+F28 -> 1278920 | G29: =G23+G28 -> 1164720 | H29: =H23+H28 -> 1028843.6 | I29: =I23+I28 -> 903851.1 | ... M29: =M23+M28 -> 976516
A31: Check (Assets − L&E, must = 0) | B31: =B17-B29 -> 0 | C31: =C17-C29 -> 0 | D31: =D17-D29 -> 0 | E31: =E17-E29 -> 0 | F31: =F17-F29 -> 0 | G31: =G17-G29 -> 0 | H31: =H17-H29 -> 0 | I31: =I17-I29 -> 0 | ... M31: =M17-M29 -> 0
